hbili_gpt
